gainr/__init__.py
gainr/api.py
gainr/dac81416.py
gainr/main.py
gainr-0.1.3.dist-info/entry_points.txt
gainr-0.1.3.dist-info/WHEEL
gainr-0.1.3.dist-info/METADATA
gainr-0.1.3.dist-info/RECORD
