Metadata-Version: 2.1
Name: gainr
Version: 0.1.3
Summary: Gainr is a HTTP API and CLI application for managing VGA amplifiers
License: Apache License, Version 2.0
Author: GreenLab
Author-email: greenlab@jinr.ru
Requires-Python: >=3.6,<4.0
Classifier: License :: Other/Proprietary License
Classifier: Programming Language :: Python :: 3
Classifier: Programming Language :: Python :: 3.6
Classifier: Programming Language :: Python :: 3.7
Classifier: Programming Language :: Python :: 3.8
Classifier: Programming Language :: Python :: 3.9
Requires-Dist: Flask (>=2.0.2,<3.0.0)
Requires-Dist: Flask-RESTful (>=0.3.9,<0.4.0)
Requires-Dist: PyYAML (>=5.3.1)
Requires-Dist: click (>=8.0.3,<9.0.0)
Requires-Dist: gpiozero (>=1.6.2,<2.0.0)
Requires-Dist: requests (>=2.26.0,<3.0.0)
